captchaOCR/__init__.py
captchaOCR/__version__.py
captchaOCR/charsets.py
captchaOCR/ocr.py
captchaOCR/utils.py
captchaOCR/onnx/common.onnx
captchaOCR/onnx/common_beta.onnx
captchaOCR-1.0.1.dist-info/LICENSE
captchaOCR-1.0.1.dist-info/METADATA
captchaOCR-1.0.1.dist-info/WHEEL
captchaOCR-1.0.1.dist-info/top_level.txt
captchaOCR-1.0.1.dist-info/RECORD
