Metadata-Version: 2.1
Name: captchaOCR
Version: 1.0.1
Summary: A OCR tool to recognize captcha
Home-page: https://github.com/Do1e/captchaOCR
Author: Do1e
Author-email: dpj.email@qq.com
Classifier: Programming Language :: Python :: 3
Classifier: License :: OSI Approved :: MIT License
Classifier: Operating System :: OS Independent
Requires-Python: >3.7
License-File: LICENSE
Requires-Dist: numpy
Requires-Dist: onnxruntime
Requires-Dist: Pillow
